internetnl_scan/__init__.py
internetnl_scan/internetnl_classes.py
internetnl_scan/main.py
internetnl_scan/utils.py
internetnl_scan-1.4.dist-info/AUTHORS.rst
internetnl_scan-1.4.dist-info/LICENSE.txt
internetnl_scan-1.4.dist-info/METADATA
internetnl_scan-1.4.dist-info/WHEEL
internetnl_scan-1.4.dist-info/entry_points.txt
internetnl_scan-1.4.dist-info/top_level.txt
internetnl_scan-1.4.dist-info/RECORD
