Metadata-Version: 2.1
Name: internetnl_scan
Version: 1.4
Summary: A python front end for submitting queries internet.nl
Home-page: https://github.com/eelcovv/internetnl-scan
Author: Eelco van Vliet
Author-email: eelcovv@gmail.com
License: mit
Project-URL: Documentation, https://internetnl-scan.readthedocs.io/en/latest/
Platform: any
Classifier: Development Status :: 4 - Beta
Classifier: Programming Language :: Python
License-File: LICENSE.txt
License-File: AUTHORS.rst
Requires-Dist: keyring
Requires-Dist: pandas
Requires-Dist: requests
Requires-Dist: tabulate
Requires-Dist: tldextract
Requires-Dist: tqdm
Requires-Dist: importlib-metadata ; python_version < "3.8"
Provides-Extra: dev
Requires-Dist: pytest ; extra == 'dev'
Requires-Dist: pytest-cov ; extra == 'dev'
Requires-Dist: sphinx ; extra == 'dev'
Requires-Dist: tox ; extra == 'dev'
Requires-Dist: black ; extra == 'dev'
Requires-Dist: pre-commit ; extra == 'dev'
Provides-Extra: proxy
Requires-Dist: requests-kerberos-proxy ; extra == 'proxy'
Provides-Extra: testing
Requires-Dist: pytest ; extra == 'testing'
Requires-Dist: pytest-cov ; extra == 'testing'
